{"jobs":[{"option_id":"op_99999999","reason":"ABS_DIFF >= 0.05","from_prob":0.85,"to_prob":0.47},{"option_id":"op_88888888","reason":"ABS_DIFF >= 0.05","from_prob":0.45,"to_prob":2.33},{"option_id":"op_4048e37b","reason":"ABS_DIFF >= 0.05","from_prob":25.26,"to_prob":22.57},{"option_id":"op_a28a22b3","reason":"ABS_DIFF >= 0.05","from_prob":95.99,"to_prob":94.6},{"option_id":"op_2bca8822","reason":"ABS_DIFF >= 0.05","from_prob":60.18,"to_prob":62.91}],"skipped":[],"stage_logs":[{"stage_id":"reeval_plan","start_ts":"2026-02-07T18:02:40.517Z","end_ts":"2026-02-07T18:02:40.517Z","dur_ms":0,"input_summary":{"abs_threshold":0.05,"rel_threshold":0.05,"speed_threshold":0.1,"staleness_min":0,"hysteresis_reset":0.02,"max_jobs":5},"output_summary":{"jobs_count":5}}]}